_lib/__init__.py
_lib/pipeline.py
_lib/pipeline_factory.py
_lib/processor.py
_lib/stage.py
_lib/concerns/__init__.py
_lib/concerns/base_pipeline.py
_lib/concerns/processable_pipeline.py
_lib/concerns/stageable_pipeline.py
_lib/contracts/__init__.py
_lib/contracts/base_pipeline.py
_lib/contracts/pipeline.py
_lib/contracts/pipeline_factory.py
_lib/contracts/processable_pipeline.py
_lib/contracts/processor.py
_lib/contracts/stage.py
_lib/contracts/stageable_pipeline.py
_lib/processors/__init__.py
_lib/processors/chained_processor/__init__.py
_lib/processors/chained_processor/chained_pipeline.py
_lib/processors/chained_processor/chained_processor.py
_lib/processors/interruptible_processor/__init__.py
_lib/processors/interruptible_processor/interruptible_pipeline.py
_lib/processors/interruptible_processor/interruptible_processor.py
_lib/support/__init__.py
_lib/support/act_as_factory/__init__.py
_lib/support/act_as_factory/act_as_factory.py
_lib/support/act_as_factory/act_as_factory_interface.py
_lib/support/clonable/__init__.py
_lib/support/clonable/clonable.py
_lib/support/clonable/clonable_interface.py
_lib/types/__init__.py
_lib/types/callable_type.py
_lib/types/types.py
thecodecrate_pipeline/__init__.py
thecodecrate_pipeline/py.typed
thecodecrate_pipeline/processors/__init__.py
thecodecrate_pipeline/types/__init__.py
thecodecrate_pipeline-1.29.0.dist-info/METADATA
thecodecrate_pipeline-1.29.0.dist-info/WHEEL
thecodecrate_pipeline-1.29.0.dist-info/licenses/LICENSE
thecodecrate_pipeline-1.29.0.dist-info/RECORD
