Metadata-Version: 2.4
Name: thecodecrate-pipeline
Version: 1.29.0
Summary: This package provides a pipeline pattern implementation
Project-URL: repository, https://github.com/thecodecrate/python-pipeline
Project-URL: documentation, https://thecodecrate.github.io/python-pipeline/
Author-email: TheCodeCrate <loureiro.rg@gmail.com>
License: The MIT License (MIT)
License-File: LICENSE
Keywords: data pipelines
Classifier: Intended Audience :: Developers
Classifier: License :: OSI Approved :: MIT License
Classifier: Programming Language :: Python
Classifier: Programming Language :: Python :: 3
Classifier: Programming Language :: Python :: 3.13
Classifier: Topic :: Software Development :: Libraries :: Python Modules
Classifier: Typing :: Typed
Requires-Python: >=3.13
